{
    "KYBERNETIKA": "0.454",
    "INT J HUM-COMPUT INT": "0.949",
    "INTERNATIONAL JOURNAL OF HUMAN-COMPUTER INTERACTION": "0.949",
    "PRESENCE-TELEOP VIRT": "0.692",
    "PRESENCE-TELEOPERATORS AND VIRTUAL ENVIRONMENTS": "0.692",
    "J COMPUT SYS SC INT+": "0.168",
    "JOURNAL OF COMPUTER AND SYSTEMS SCIENCES INTERNATIONAL": "0.168",
    "IEEE T SYST MAN CY B": "3.080",
    "IEEE TRANSACTIONS ON SYSTEMS MAN AND CYBERNETICS PART B-CYBERNETICS": "3.080",
    "IEEE T SYST MAN CY C": "2.009",
    "IEEE TRANSACTIONS ON SYSTEMS MAN AND CYBERNETICS PART C-APPLICATIONS AND RE": "2.009",
    "IEEE T SYST MAN CY A": "2.123",
    "IEEE TRANSACTIONS ON SYSTEMS MAN AND CYBERNETICS PART A-SYSTEMS AND HUMANS": "2.123",
    "INT J HUM-COMPUT ST": "1.171",
    "INTERNATIONAL JOURNAL OF HUMAN-COMPUTER STUDIES": "1.171",
    "BEHAV INFORM TECHNOL": "1.011",
    "BEHAVIOUR & INFORMATION TECHNOLOGY": "1.011",
    "CYBERNET SYST": "1.182",
    "CYBERNETICS AND SYSTEMS": "1.182",
    "KYBERNETES": "0.240",
    "CONTROL CYBERN": "",
    "CONTROL AND CYBERNETICS": "",
    "BIOL CYBERN": "1.586",
    "BIOLOGICAL CYBERNETICS": "1.586",
    "HUM-COMPUT INTERACT": "1.476",
    "HUMAN-COMPUTER INTERACTION": "1.476",
    "USER MODEL USER-ADAP": "1.400",
    "USER MODELING AND USER-ADAPTED INTERACTION": "1.400",
    "MACH VISION APPL": "1.009",
    "MACHINE VISION AND APPLICATIONS": "1.009",
    "INTERACT COMPUT": "1.233",
    "INTERACTING WITH COMPUTERS": "1.233",
    "OPTIM METHOD SOFTW": "0.651",
    "OPTIMIZATION METHODS & SOFTWARE": "0.651",
    "ACM T SOFTW ENG METH": "1.269",
    "ACM TRANSACTIONS ON SOFTWARE ENGINEERING AND METHODOLOGY": "1.269",
    "IEEE T RELIAB": "1.285",
    "IEEE TRANSACTIONS ON RELIABILITY": "1.285",
    "J NETW COMPUT APPL": "1.065",
    "JOURNAL OF NETWORK AND COMPUTER APPLICATIONS": "1.065",
    "SIMUL-T SOC MOD SIM": "0.793",
    "SIMULATION-TRANSACTIONS OF THE SOCIETY FOR MODELING AND SIMULATION INTERNATIONAL": "0.793",
    "COMMUN ACM": "1.919",
    "COMMUNICATIONS OF THE ACM": "1.919",
    "IEEE INTERNET COMPUT": "2.000",
    "IEEE INTERNET COMPUTING": "2.000",
    "IEEE T VIS COMPUT GR": "2.215",
    "IEEE TRANSACTIONS ON VISUALIZATION AND COMPUTER GRAPHICS": "2.215",
    "SOFTWARE PRACT EXPER": "0.519",
    "SOFTWARE-PRACTICE & EXPERIENCE": "0.519",
    "J COMPUT SCI TECHNOL": "0.564",
    "JOURNAL OF COMPUTER SCIENCE AND TECHNOLOGY": "0.564",
    "COMPUT GRAPH-UK": "1.000",
    "COMPUTERS & GRAPHICS-UK": "1.000",
    "IEEE T SOFTWARE ENG": "1.980",
    "IEEE TRANSACTIONS ON SOFTWARE ENGINEERING": "1.980",
    "ACM T DES AUTOMAT EL": "0.811",
    "ACM TRANSACTIONS ON DESIGN AUTOMATION OF ELECTRONIC SYSTEMS": "0.811",
    "COMPUT J": "0.785",
    "COMPUTER JOURNAL": "0.785",
    "J VISUAL LANG COMPUT": "0.481",
    "JOURNAL OF VISUAL LANGUAGES AND COMPUTING": "0.481",
    "J VIS COMMUN IMAGE R": "1.122",
    "JOURNAL OF VISUAL COMMUNICATION AND IMAGE REPRESENTATION": "1.122",
    "J DATABASE MANAGE": "0.875",
    "JOURNAL OF DATABASE MANAGEMENT": "0.875",
    "ACM T MATH SOFTWARE": "1.922",
    "ACM TRANSACTIONS ON MATHEMATICAL SOFTWARE": "1.922",
    "IEEE MULTIMEDIA": "0.438",
    "BIT": "0.724",
    "BIT NUMERICAL MATHEMATICS": "0.724",
    "RANDOM STRUCT ALGOR": "1.034",
    "RANDOM STRUCTURES & ALGORITHMS": "1.034",
    "MATH PROGRAM": "1.707",
    "MATHEMATICAL PROGRAMMING": "1.707",
    "COMPUTER": "1.470",
    "DR DOBBS J": "0.000",
    "DR DOBBS JOURNAL": "0.000",
    "IBM SYST J": "",
    "IBM SYSTEMS JOURNAL": "",
    "ADV COMPUT": "0.342",
    "ADVANCES IN COMPUTERS": "0.342",
    "COMPUT AIDED DESIGN": "1.234",
    "COMPUTER-AIDED DESIGN": "1.234",
    "J ACM": "2.353",
    "JOURNAL OF THE ACM": "2.353",
    "INT J ELECTRON COMM": "1.550",
    "INTERNATIONAL JOURNAL OF ELECTRONIC COMMERCE": "1.550",
    "SCI COMPUT PROGRAM": "0.622",
    "SCIENCE OF COMPUTER PROGRAMMING": "0.622",
    "ACM T PROGR LANG SYS": "0.950",
    "ACM TRANSACTIONS ON PROGRAMMING LANGUAGES AND SYSTEMS": "0.950",
    "COMPUT GRAPH FORUM": "1.634",
    "COMPUTER GRAPHICS FORUM": "1.634",
    "J SYST SOFTWARE": "0.836",
    "JOURNAL OF SYSTEMS AND SOFTWARE": "0.836",
    "COMPUT AIDED GEOM D": "1.054",
    "COMPUTER AIDED GEOMETRIC DESIGN": "1.054",
    "VISUAL COMPUT": "0.576",
    "VISUAL COMPUTER": "0.576",
    "SIGMOD REC": "0.667",
    "SIGMOD RECORD": "0.667",
    "ALGORITHMICA": "0.604",
    "FUND INFORM": "0.365",
    "FUNDAMENTA INFORMATICAE": "0.365",
    "IEEE MICRO": "1.783",
    "INT J SOFTW ENG KNOW": "0.129",
    "INTERNATIONAL JOURNAL OF SOFTWARE ENGINEERING AND KNOWLEDGE ENGINEERING": "0.129",
    "IMAGE VISION COMPUT": "1.723",
    "IMAGE AND VISION COMPUTING": "1.723",
    "COMPUT GRAPH WORLD": "0.015",
    "COMPUTER GRAPHICS WORLD": "0.015",
    "IEEE COMPUT GRAPH": "1.411",
    "IEEE COMPUTER GRAPHICS AND APPLICATIONS": "1.411",
    "INT J WAVELETS MULTI": "",
    "INTERNATIONAL JOURNAL OF WAVELETS MULTIRESOLUTION AND INFORMATION PROCESSING": "",
    "ACM SIGPLAN NOTICES": "0.090",
    "MULTIMED TOOLS APPL": "0.617",
    "MULTIMEDIA TOOLS AND APPLICATIONS": "0.617",
    "PROGRAM COMPUT SOFT+": "0.090",
    "PROGRAMMING AND COMPUTER SOFTWARE": "0.090",
    "ICGA J": "1.154",
    "ICGA JOURNAL": "1.154",
    "EMPIR SOFTW ENG": "1.854",
    "EMPIRICAL SOFTWARE ENGINEERING": "1.854",
    "ACM T DATABASE SYST": "1.000",
    "ACM TRANSACTIONS ON DATABASE SYSTEMS": "1.000",
    "MATH COMPUT SIMULAT": "0.738",
    "MATHEMATICS AND COMPUTERS IN SIMULATION": "0.738",
    "WORLD WIDE WEB": "0.513",
    "WORLD WIDE WEB-INTERNET AND WEB INFORMATION SYSTEMS": "0.513",
    "DISCRETE MATH THEOR": "",
    "DISCRETE MATHEMATICS AND THEORETICAL COMPUTER SCIENCE": "",
    "IEE P-SOFTW": "",
    "IEE PROCEEDINGS-SOFTWARE": "",
    "THEOR PRACT LOG PROG": "0.667",
    "THEORY AND PRACTICE OF LOGIC PROGRAMMING": "0.667",
    "COMPUT LANG SYST STR": "0.273",
    "COMPUTER LANGUAGES SYSTEMS & STRUCTURES": "0.273",
    "J RES PRACT INF TECH": "0.105",
    "JOURNAL OF RESEARCH AND PRACTICE IN INFORMATION TECHNOLOGY": "0.105",
    "SIMUL MODEL PRACT TH": "0.969",
    "SIMULATION MODELLING PRACTICE AND THEORY": "0.969",
    "J WEB SEMANT": "1.302",
    "JOURNAL OF WEB SEMANTICS": "1.302",
    "IEEE T DEPEND SECURE": "1.140",
    "IEEE TRANSACTIONS ON DEPENDABLE AND SECURE COMPUTING": "1.140",
    "IEEE T MULTIMEDIA": "1.935",
    "IEEE TRANSACTIONS ON MULTIMEDIA": "1.935",
    "J WEB ENG": "0.156",
    "JOURNAL OF WEB ENGINEERING": "0.156",
    "J SOFTW MAINT EVOL-R": "0.844",
    "JOURNAL OF SOFTWARE MAINTENANCE AND EVOLUTION-RESEARCH AND PRACTICE": "0.844",
    "INT J WEB SERV RES": "0.371",
    "INTERNATIONAL JOURNAL OF WEB SERVICES RESEARCH": "0.371",
    "IEEE SECUR PRIV": "0.898",
    "IEEE SECURITY & PRIVACY": "0.898",
    "COMPUT ANIMAT VIRT W": "0.394",
    "COMPUTER ANIMATION AND VIRTUAL WORLDS": "0.394",
    "ACM T MULTIM COMPUT": "0.850",
    "ACM TRANSACTIONS ON MULTIMEDIA COMPUTING COMMUNICATIONS AND APPLICATIONS": "0.850",
    "GRAPH MODELS": "1.000",
    "GRAPHICAL MODELS": "1.000",
    "CONCURR COMP-PRACT E": "0.636",
    "CONCURRENCY AND COMPUTATION-PRACTICE & EXPERIENCE": "0.636",
    "IET SOFTW": "0.329",
    "IET SOFTWARE": "0.329",
    "ACM T GRAPHIC": "3.489",
    "ACM TRANSACTIONS ON GRAPHICS": "3.489",
    "IEEE SOFTWARE": "1.508",
    "MATH COMPUT MODEL": "1.346",
    "MATHEMATICAL AND COMPUTER MODELLING": "1.346",
    "J MATH IMAGING VIS": "1.391",
    "JOURNAL OF MATHEMATICAL IMAGING AND VISION": "1.391",
    "REQUIR ENG": "0.971",
    "REQUIREMENTS ENGINEERING": "0.971",
    "SOFTW TEST VERIF REL": "0.957",
    "SOFTWARE TESTING VERIFICATION & RELIABILITY": "0.957",
    "J FUNCT PROGRAM": "0.878",
    "JOURNAL OF FUNCTIONAL PROGRAMMING": "0.878",
    "INFORM SOFTWARE TECH": "1.250",
    "INFORMATION AND SOFTWARE TECHNOLOGY": "1.250",
    "ADV ENG SOFTW": "1.092",
    "ADVANCES IN ENGINEERING SOFTWARE": "1.092",
    "COMPUT STAND INTER": "1.257",
    "COMPUTER STANDARDS & INTERFACES": "1.257",
    "SOFTWARE QUAL J": "0.417",
    "SOFTWARE QUALITY JOURNAL": "0.417",
    "DES AUTOM EMBED SYST": "0.200",
    "DESIGN AUTOMATION FOR EMBEDDED SYSTEMS": "0.200",
    "J UNIVERS COMPUT SCI": "0.398",
    "JOURNAL OF UNIVERSAL COMPUTER SCIENCE": "0.398",
    "IEICE T INF SYST": "0.178",
    "IEICE TRANSACTIONS ON INFORMATION AND SYSTEMS": "0.178",
    "FORM ASP COMPUT": "0.463",
    "FORMAL ASPECTS OF COMPUTING": "0.463",
    "INT J HIGH PERFORM C": "0.643",
    "INTERNATIONAL JOURNAL OF HIGH PERFORMANCE COMPUTING APPLICATIONS": "0.643",
    "COMPUTING": "0.701",
    "J COMPUT SYST SCI": "1.157",
    "JOURNAL OF COMPUTER AND SYSTEM SCIENCES": "1.157",
    "INT J SYST SCI": "0.991",
    "INTERNATIONAL JOURNAL OF SYSTEMS SCIENCE": "0.991",
    "SIAM J COMPUT": "1.288",
    "SIAM JOURNAL ON COMPUTING": "1.288",
    "IEEE T PARALL DISTR": "1.402",
    "IEEE TRANSACTIONS ON PARALLEL AND DISTRIBUTED SYSTEMS": "1.402",
    "IEEE ANN HIST COMPUT": "0.378",
    "IEEE ANNALS OF THE HISTORY OF COMPUTING": "0.378",
    "ARTIF LIFE": "2.282",
    "ARTIFICIAL LIFE": "2.282",
    "IEEE T EVOLUT COMPUT": "3.341",
    "IEEE TRANSACTIONS ON EVOLUTIONARY COMPUTATION": "3.341",
    "EVOL COMPUT": "1.061",
    "EVOLUTIONARY COMPUTATION": "1.061",
    "COMPUT COMPLEX": "1.122",
    "COMPUTATIONAL COMPLEXITY": "1.122",
    "IEEE ACM T NETWORK": "2.033",
    "IEEE-ACM TRANSACTIONS ON NETWORKING": "2.033",
    "IEEE T NEURAL NETWOR": "2.952",
    "IEEE TRANSACTIONS ON NEURAL NETWORKS": "2.952",
    "COMPUT METH PROG BIO": "1.516",
    "COMPUTER METHODS AND PROGRAMS IN BIOMEDICINE": "1.516",
    "PERFORM EVALUATION": "0.791",
    "PERFORMANCE EVALUATION": "0.791",
    "J ALGORITHM": "0.500",
    "JOURNAL OF ALGORITHMS": "0.500",
    "PARALLEL COMPUT": "1.311",
    "PARALLEL COMPUTING": "1.311",
    "CRYPTOLOGIA": "0.109",
    "DISCRETE COMPUT GEOM": "0.938",
    "DISCRETE & COMPUTATIONAL GEOMETRY": "0.938",
    "INT J FOUND COMPUT S": "0.379",
    "INTERNATIONAL JOURNAL OF FOUNDATIONS OF COMPUTER SCIENCE": "0.379",
    "DISTRIB COMPUT": "0.976",
    "DISTRIBUTED COMPUTING": "0.976",
    "FUTURE GENER COMP SY": "1.978",
    "FUTURE GENERATION COMPUTER SYSTEMS": "1.978",
    "FUZZY SET SYST": "1.759",
    "FUZZY SETS AND SYSTEMS": "1.759",
    "MICROPROCESS MICROSY": "0.575",
    "MICROPROCESSORS AND MICROSYSTEMS": "0.575",
    "NEW GENERAT COMPUT": "0.941",
    "NEW GENERATION COMPUTING": "0.941",
    "EXPERT SYST": "0.684",
    "EXPERT SYSTEMS": "0.684",
    "INT J QUANTUM INF": "0.670",
    "INTERNATIONAL JOURNAL OF QUANTUM INFORMATION": "0.670",
    "COMPUT SYST SCI ENG": "0.371",
    "COMPUTER SYSTEMS SCIENCE AND ENGINEERING": "0.371",
    "INT J COMPUT GEOM AP": "0.292",
    "INTERNATIONAL JOURNAL OF COMPUTATIONAL GEOMETRY & APPLICATIONS": "0.292",
    "THEOR COMPUT SCI": "0.665",
    "THEORETICAL COMPUTER SCIENCE": "0.665",
    "CONSTRAINTS": "0.659",
    "ACM COMPUT SURV": "4.529",
    "ACM COMPUTING SURVEYS": "4.529",
    "J HEURISTICS": "1.262",
    "JOURNAL OF HEURISTICS": "1.262",
    "CLUSTER COMPUT": "0.519",
    "CLUSTER COMPUTING-THE JOURNAL OF NETWORKS SOFTWARE TOOLS AND APPLICATIONS": "0.519",
    "INFORM SYST FRONT": "0.912",
    "INFORMATION SYSTEMS FRONTIERS": "0.912",
    "INT J GEN SYST": "0.667",
    "INTERNATIONAL JOURNAL OF GENERAL SYSTEMS": "0.667",
    "THEOR COMPUT SYST": "0.442",
    "THEORY OF COMPUTING SYSTEMS": "0.442",
    "IEEE T INF FOREN SEC": "1.340",
    "IEEE TRANSACTIONS ON INFORMATION FORENSICS AND SECURITY": "1.340",
    "J MULT-VALUED LOG S": "0.260",
    "JOURNAL OF MULTIPLE-VALUED LOGIC AND SOFT COMPUTING": "0.260",
    "INFORM FUSION": "1.467",
    "INFORMATION FUSION": "1.467",
    "ACM T COMPUT LOG": "0.823",
    "ACM TRANSACTIONS ON COMPUTATIONAL LOGIC": "0.823",
    "J CELL AUTOM": "0.340",
    "JOURNAL OF CELLULAR AUTOMATA": "0.340",
    "QUANTUM INF COMPUT": "1.659",
    "QUANTUM INFORMATION & COMPUTATION": "1.659",
    "J LOGIC ALGEBR PROGR": "0.506",
    "JOURNAL OF LOGIC AND ALGEBRAIC PROGRAMMING": "0.506",
    "J COMPUT ANAL APPL": "0.417",
    "JOURNAL OF COMPUTATIONAL ANALYSIS AND APPLICATIONS": "0.417",
    "J ZHEJIANG UNIV-SC A": "0.408",
    "JOURNAL OF ZHEJIANG UNIVERSITY-SCIENCE A": "0.408",
    "FOUND COMPUT MATH": "3.615",
    "FOUNDATIONS OF COMPUTATIONAL MATHEMATICS": "3.615",
    "J SYMB COMPUT": "0.707",
    "JOURNAL OF SYMBOLIC COMPUTATION": "0.707",
    "IET COMPUT DIGIT TEC": "0.446",
    "IET COMPUTERS AND DIGITAL TECHNIQUES": "0.446",
    "IET INFORM SECUR": "0.143",
    "IET INFORMATION SECURITY": "0.143",
    "J PARALLEL DISTR COM": "0.859",
    "JOURNAL OF PARALLEL AND DISTRIBUTED COMPUTING": "0.859",
    "ACM T COMPUT SYST": "1.188",
    "ACM TRANSACTIONS ON COMPUTER SYSTEMS": "1.188",
    "INFORM COMPUT": "0.560",
    "INFORMATION AND COMPUTATION": "0.560",
    "INT J PARALLEL PROG": "0.569",
    "INTERNATIONAL JOURNAL OF PARALLEL PROGRAMMING": "0.569",
    "J COMPLEXITY": "1.099",
    "JOURNAL OF COMPLEXITY": "1.099",
    "COMB PROBAB COMPUT": "0.778",
    "COMBINATORICS PROBABILITY & COMPUTING": "0.778",
    "J CRYPTOL": "1.250",
    "JOURNAL OF CRYPTOLOGY": "1.250",
    "FORM METHOD SYST DES": "0.690",
    "FORMAL METHODS IN SYSTEM DESIGN": "0.690",
    "STAT COMPUT": "1.429",
    "STATISTICS AND COMPUTING": "1.429",
    "J SUPERCOMPUT": "0.578",
    "JOURNAL OF SUPERCOMPUTING": "0.578",
    "DESIGN CODE CRYPTOGR": "0.875",
    "DESIGNS CODES AND CRYPTOGRAPHY": "0.875",
    "REAL-TIME SYST": "0.738",
    "REAL-TIME SYSTEMS": "0.738",
    "CONNECT SCI": "0.676",
    "CONNECTION SCIENCE": "0.676",
    "MULTIMEDIA SYST": "0.729",
    "MULTIMEDIA SYSTEMS": "0.729",
    "MULTIDIM SYST SIGN P": "0.953",
    "MULTIDIMENSIONAL SYSTEMS AND SIGNAL PROCESSING": "0.953",
    "ADV MATH COMMUN": "0.462",
    "ADVANCES IN MATHEMATICS OF COMMUNICATIONS": "0.462",
    "MATH STRUCT COMP SCI": "0.690",
    "MATHEMATICAL STRUCTURES IN COMPUTER SCIENCE": "0.690",
    "APPL ALGEBR ENG COMM": "0.600",
    "APPLICABLE ALGEBRA IN ENGINEERING COMMUNICATION AND COMPUTING": "0.600",
    "DISTRIB PARALLEL DAT": "0.286",
    "DISTRIBUTED AND PARALLEL DATABASES": "0.286",
    "J LOGIC COMPUT": "0.611",
    "JOURNAL OF LOGIC AND COMPUTATION": "0.611",
    "INFORM SYST MANAGE": "0.578",
    "INFORMATION SYSTEMS MANAGEMENT": "0.578",
    "SCI CHINA SER F": "0.656",
    "SCIENCE IN CHINA SERIES F-INFORMATION SCIENCES": "0.656",
    "BELL LABS TECH J": "0.880",
    "BELL LABS TECHNICAL JOURNAL": "0.880",
    "INFORM SCIENCES": "2.833",
    "INFORMATION SCIENCES": "2.833",
    "IEEE T KNOWL DATA EN": "1.657",
    "IEEE TRANSACTIONS ON KNOWLEDGE AND DATA ENGINEERING": "1.657",
    "INFORM PROCESS LETT": "0.455",
    "INFORMATION PROCESSING LETTERS": "0.455",
    "WIREL NETW": "0.520",
    "WIRELESS NETWORKS": "0.520",
    "ASLIB PROC": "0.635",
    "ASLIB PROCEEDINGS": "0.635",
    "ACTA INFORM": "0.444",
    "ACTA INFORMATICA": "0.444",
    "J NETW SYST MANAG": "0.452",
    "JOURNAL OF NETWORK AND SYSTEMS MANAGEMENT": "0.452",
    "ANNU REV INFORM SCI": "2.955",
    "ANNUAL REVIEW OF INFORMATION SCIENCE AND TECHNOLOGY": "2.955",
    "IEEE T INF TECHNOL B": "1.676",
    "IEEE TRANSACTIONS ON INFORMATION TECHNOLOGY IN BIOMEDICINE": "1.676",
    "INTERNET RES": "1.115",
    "INTERNET RESEARCH-ELECTRONIC NETWORKING APPLICATIONS AND POLICY": "1.115",
    "J INF SCI ENG": "0.175",
    "JOURNAL OF INFORMATION SCIENCE AND ENGINEERING": "0.175",
    "METHOD INFORM MED": "1.532",
    "METHODS OF INFORMATION IN MEDICINE": "1.532",
    "J AM MED INFORM ASSN": "3.609",
    "JOURNAL OF THE AMERICAN MEDICAL INFORMATICS ASSOCIATION": "3.609",
    "VLDB J": "1.564",
    "VLDB JOURNAL": "1.564",
    "J ORG COMP ELECT COM": "0.344",
    "JOURNAL OF ORGANIZATIONAL COMPUTING AND ELECTRONIC COMMERCE": "0.344",
    "PROGRAM-ELECTRON LIB": "0.283",
    "PROGRAM-ELECTRONIC LIBRARY AND INFORMATION SYSTEMS": "0.283",
    "ACM T INFORM SYST": "1.077",
    "ACM TRANSACTIONS ON INFORMATION SYSTEMS": "1.077",
    "IEEE T INFORM THEORY": "3.009",
    "IEEE TRANSACTIONS ON INFORMATION THEORY": "3.009",
    "COMPUT SECUR": "0.868",
    "COMPUTERS & SECURITY": "0.868",
    "J INF SCI": "1.299",
    "JOURNAL OF INFORMATION SCIENCE": "1.299",
    "DATA KNOWL ENG": "1.422",
    "DATA & KNOWLEDGE ENGINEERING": "1.422",
    "COMPUT COMMUN REV": "0.648",
    "COMPUTER COMMUNICATION REVIEW": "0.648",
    "DECIS SUPPORT SYST": "1.687",
    "DECISION SUPPORT SYSTEMS": "1.687",
    "COMPUT COMMUN": "1.044",
    "COMPUTER COMMUNICATIONS": "1.044",
    "OPEN SYST INF DYN": "1.167",
    "OPEN SYSTEMS & INFORMATION DYNAMICS": "1.167",
    "KNOWL INF SYST": "2.225",
    "KNOWLEDGE AND INFORMATION SYSTEMS": "2.225",
    "J COMMUN NETW-S KOR": "0.291",
    "JOURNAL OF COMMUNICATIONS AND NETWORKS": "0.291",
    "J INF TECHNOL": "2.321",
    "JOURNAL OF INFORMATION TECHNOLOGY": "2.321",
    "MIS QUART": "4.447",
    "MIS QUARTERLY": "4.447",
    "INT J COOP INF SYST": "1.278",
    "INTERNATIONAL JOURNAL OF COOPERATIVE INFORMATION SYSTEMS": "1.278",
    "INT J INF TECH DECIS": "",
    "INTERNATIONAL JOURNAL OF INFORMATION TECHNOLOGY & DECISION MAKING": "",
    "INFOR": "0.295",
    "COMPUT NETW": "1.200",
    "COMPUTER NETWORKS-THE INTERNATIONAL JOURNAL OF COMPUTER AND TELECOMMUNICATI": "1.200",
    "GEOINFORMATICA": "1.143",
    "MOBILE NETW APPL": "0.838",
    "MOBILE NETWORKS & APPLICATIONS": "0.838",
    "INFORM SYST": "1.198",
    "INFORMATION SYSTEMS": "1.198",
    "INT J GEOGR INF SCI": "1.472",
    "INTERNATIONAL JOURNAL OF GEOGRAPHICAL INFORMATION SCIENCE": "1.472",
    "INFORM MANAGE-AMSTER": "2.214",
    "INFORMATION & MANAGEMENT": "2.214",
    "DATA MIN KNOWL DISC": "1.545",
    "DATA MINING AND KNOWLEDGE DISCOVERY": "1.545",
    "INFORM RETRIEVAL": "0.914",
    "INFORMATION RETRIEVAL": "0.914",
    "INFORM PROCESS MANAG": "1.119",
    "INFORMATION PROCESSING & MANAGEMENT": "1.119",
    "INT J MED INFORM": "2.414",
    "INTERNATIONAL JOURNAL OF MEDICAL INFORMATICS": "2.414",
    "PHOTONIC NETW COMMUN": "0.485",
    "PHOTONIC NETWORK COMMUNICATIONS": "0.485",
    "MED INFORM INTERNET": "",
    "MEDICAL INFORMATICS AND THE INTERNET IN MEDICINE": "",
    "ONLINE INFORM REV": "0.939",
    "ONLINE INFORMATION REVIEW": "0.939",
    "J ASSOC INF SYST": "1.667",
    "JOURNAL OF THE ASSOCIATION FOR INFORMATION SYSTEMS": "1.667",
    "J AM SOC INF SCI TEC": "2.081",
    "JOURNAL OF THE AMERICAN SOCIETY FOR INFORMATION SCIENCE AND TECHNOLOGY": "2.081",
    "IEEE PERVAS COMPUT": "1.554",
    "IEEE PERVASIVE COMPUTING": "1.554",
    "IEEE WIREL COMMUN": "2.575",
    "IEEE WIRELESS COMMUNICATIONS": "2.575",
    "IEEE T MOBILE COMPUT": "2.283",
    "IEEE TRANSACTIONS ON MOBILE COMPUTING": "2.283",
    "INT J SEMANT WEB INF": "2.308",
    "INTERNATIONAL JOURNAL ON SEMANTIC WEB AND INFORMATION SYSTEMS": "2.308",
    "J CHEM INF MODEL": "4.675",
    "JOURNAL OF CHEMICAL INFORMATION AND MODELING": "4.675",
    "INT J DISTRIB SENS N": "0.203",
    "INTERNATIONAL JOURNAL OF DISTRIBUTED SENSOR NETWORKS": "0.203",
    "WIREL COMMUN MOB COM": "0.884",
    "WIRELESS COMMUNICATIONS & MOBILE COMPUTING": "0.884",
    "ELECTRON COMMER R A": "1.472",
    "ELECTRONIC COMMERCE RESEARCH AND APPLICATIONS": "1.472",
    "J OPT NETW": "1.079",
    "JOURNAL OF OPTICAL NETWORKING": "1.079",
    "PERS UBIQUIT COMPUT": "0.938",
    "PERSONAL AND UBIQUITOUS COMPUTING": "0.938",
    "DIGIT INVEST": "0.507",
    "DIGITAL INVESTIGATION": "0.507",
    "J MANAGE INFORM SYST": "1.423",
    "JOURNAL OF MANAGEMENT INFORMATION SYSTEMS": "1.423",
    "INFORM TECHNOL LIBR": "0.250",
    "INFORMATION TECHNOLOGY AND LIBRARIES": "0.250",
    "INFORMATICA-LITHUAN": "1.627",
    "INFORMATICA": "1.627",
    "IEEE NETWORK": "2.239",
    "J SIGNAL PROCESS SYS": "0.672",
    "JOURNAL OF SIGNAL PROCESSING SYSTEMS FOR SIGNAL IMAGE AND VIDEO TECHNOLOGY": "0.672",
    "IEICE T FUND ELECTR": "0.226",
    "IEICE TRANSACTIONS ON FUNDAMENTALS OF ELECTRONICS COMMUNICATIONS AND COMPUT": "0.226",
    "WIRTSCHAFTSINF": "",
    "WIRTSCHAFTSINFORMATIK": "",
    "J HIGH SPEED NETW": "",
    "JOURNAL OF HIGH SPEED NETWORKS": "",
    "RAIRO-THEOR INF APPL": "0.397",
    "RAIRO-THEORETICAL INFORMATICS AND APPLICATIONS": "0.397",
    "J INTELL INF SYST": "0.618",
    "JOURNAL OF INTELLIGENT INFORMATION SYSTEMS": "0.618",
    "EUR J INFORM SYST": "1.500",
    "EUROPEAN JOURNAL OF INFORMATION SYSTEMS": "1.500",
    "J STRATEGIC INF SYST": "1.457",
    "JOURNAL OF STRATEGIC INFORMATION SYSTEMS": "1.457",
    "J VLSI SIG PROC SYST": "",
    "JOURNAL OF VLSI SIGNAL PROCESSING SYSTEMS FOR SIGNAL IMAGE AND VIDEO TECHNO": "",
    "COMPUT BIOL MED": "1.089",
    "COMPUTERS IN BIOLOGY AND MEDICINE": "1.089",
    "COMPUT STRUCT": "1.874",
    "COMPUTERS & STRUCTURES": "1.874",
    "J COMPUT BIOL": "1.546",
    "JOURNAL OF COMPUTATIONAL BIOLOGY": "1.546",
    "J MOL GRAPH MODEL": "2.184",
    "JOURNAL OF MOLECULAR GRAPHICS & MODELLING": "2.184",
    "CONCURRENT ENG-RES A": "0.478",
    "CONCURRENT ENGINEERING-RESEARCH AND APPLICATIONS": "0.478",
    "INTEGR COMPUT-AID E": "3.451",
    "INTEGRATED COMPUTER-AIDED ENGINEERING": "3.451",
    "SAR QSAR ENVIRON RES": "2.086",
    "SAR AND QSAR IN ENVIRONMENTAL RESEARCH": "2.086",
    "COMPUT METHOD BIOMEC": "0.849",
    "COMPUTER METHODS IN BIOMECHANICS AND BIOMEDICAL ENGINEERING": "0.849",
    "INT J RF MICROW C E": "0.591",
    "INTERNATIONAL JOURNAL OF RF AND MICROWAVE COMPUTER-AIDED ENGINEERING": "0.591",
    "COMPUT ELECTR ENG": "0.837",
    "COMPUTERS & ELECTRICAL ENGINEERING": "0.837",
    "COMPUT CHEM ENG": "2.320",
    "COMPUTERS & CHEMICAL ENGINEERING": "2.320",
    "COMPUT APPL ENG EDUC": "0.333",
    "COMPUTER APPLICATIONS IN ENGINEERING EDUCATION": "0.333",
    "COMPUT FLUIDS": "1.810",
    "COMPUTERS & FLUIDS": "1.810",
    "COMPUT GEOSCI-UK": "1.429",
    "COMPUTERS & GEOSCIENCES": "1.429",
    "INFORMS J COMPUT": "1.076",
    "INFORMS JOURNAL ON COMPUTING": "1.076",
    "ACM T MODEL COMPUT S": "1.114",
    "ACM TRANSACTIONS ON MODELING AND COMPUTER SIMULATION": "1.114",
    "COMPUT PHYS COMMUN": "3.268",
    "COMPUTER PHYSICS COMMUNICATIONS": "3.268",
    "J COMPUT PHYS": "2.310",
    "JOURNAL OF COMPUTATIONAL PHYSICS": "2.310",
    "J STAT COMPUT SIM": "0.497",
    "JOURNAL OF STATISTICAL COMPUTATION AND SIMULATION": "0.497",
    "COMPUT-AIDED CIV INF": "3.382",
    "COMPUTER-AIDED CIVIL AND INFRASTRUCTURE ENGINEERING": "3.382",
    "COMPUT ELECTRON AGR": "1.846",
    "COMPUTERS AND ELECTRONICS IN AGRICULTURE": "1.846",
    "ENG COMPUT-GERMANY": "0.739",
    "ENGINEERING WITH COMPUTERS": "0.739",
    "MED BIOL ENG COMPUT": "1.878",
    "MEDICAL & BIOLOGICAL ENGINEERING & COMPUTING": "1.878",
    "COMPUT MUSIC J": "0.706",
    "COMPUTER MUSIC JOURNAL": "0.706",
    "SPEECH COMMUN": "1.267",
    "SPEECH COMMUNICATION": "1.267",
    "COMPUT IND": "1.529",
    "COMPUTERS IN INDUSTRY": "1.529",
    "INT J MOD PHYS C": "0.570",
    "INTERNATIONAL JOURNAL OF MODERN PHYSICS C": "0.570",
    "ARCH COMPUT METHOD E": "2.767",
    "ARCHIVES OF COMPUTATIONAL METHODS IN ENGINEERING": "2.767",
    "COMPUT STAT DATA AN": "1.028",
    "COMPUTATIONAL STATISTICS & DATA ANALYSIS": "1.028",
    "SCIENTOMETRICS": "1.966",
    "INT J NUMER METH FL": "1.176",
    "INTERNATIONAL JOURNAL FOR NUMERICAL METHODS IN FLUIDS": "1.176",
    "INT J ARTIF INTELL T": "0.217",
    "INTERNATIONAL JOURNAL ON ARTIFICIAL INTELLIGENCE TOOLS": "0.217",
    "QUEUEING SYST": "0.717",
    "QUEUEING SYSTEMS": "0.717",
    "ENG COMPUTATION": "1.060",
    "ENGINEERING COMPUTATIONS": "1.060",
    "IEEE T COMPUT AID D": "1.271",
    "IEEE TRANSACTIONS ON COMPUTER-AIDED DESIGN OF INTEGRATED CIRCUITS AND SYSTE": "1.271",
    "COMPUT GEOTECH": "0.987",
    "COMPUTERS AND GEOTECHNICS": "0.987",
    "IND MANAGE DATA SYST": "1.472",
    "INDUSTRIAL MANAGEMENT & DATA SYSTEMS": "1.472",
    "IEEE T MED IMAGING": "3.643",
    "IEEE TRANSACTIONS ON MEDICAL IMAGING": "3.643",
    "J VISUAL-JAPAN": "0.435",
    "JOURNAL OF VISUALIZATION": "0.435",
    "ENVIRON MODELL SOFTW": "3.114",
    "ENVIRONMENTAL MODELLING & SOFTWARE": "3.114",
    "MED IMAGE ANAL": "4.424",
    "MEDICAL IMAGE ANALYSIS": "4.424",
    "MATH COMP MODEL DYN": "0.406",
    "MATHEMATICAL AND COMPUTER MODELLING OF DYNAMICAL SYSTEMS": "0.406",
    "COMPUT IND ENG": "1.589",
    "COMPUTERS & INDUSTRIAL ENGINEERING": "1.589",
    "J COMB OPTIM": "0.664",
    "JOURNAL OF COMBINATORIAL OPTIMIZATION": "0.664",
    "COMPEL": "0.301",
    "COMPEL-THE INTERNATIONAL JOURNAL FOR COMPUTATION AND MATHEMATICS IN ELECTRI": "0.301",
    "COMPUT OPER RES": "1.720",
    "COMPUTERS & OPERATIONS RESEARCH": "1.720",
    "BIOINFORMATICS": "5.468",
    "COMPUT EDUC": "2.621",
    "COMPUTERS & EDUCATION": "2.621",
    "MATCH-COMMUN MATH CO": "2.161",
    "MATCH-COMMUNICATIONS IN MATHEMATICAL AND IN COMPUTER CHEMISTRY": "2.161",
    "COMPUTAT GEOSCI": "1.348",
    "COMPUTATIONAL GEOSCIENCES": "1.348",
    "COMPUT BIOL CHEM": "1.551",
    "COMPUTATIONAL BIOLOGY AND CHEMISTRY": "1.551",
    "J HYDROINFORM": "1.048",
    "JOURNAL OF HYDROINFORMATICS": "1.048",
    "SOFT COMPUT": "1.880",
    "SOFT COMPUTING": "1.880",
    "IEEE ACM T COMPUT BI": "1.543",
    "IEEE-ACM TRANSACTIONS ON COMPUTATIONAL BIOLOGY AND BIOINFORMATICS": "1.543",
    "J STAT SOFTW": "4.010",
    "JOURNAL OF STATISTICAL SOFTWARE": "4.010",
    "IEEE T IND INFORM": "2.990",
    "IEEE TRANSACTIONS ON INDUSTRIAL INFORMATICS": "2.990",
    "APPL SOFT COMPUT": "2.612",
    "APPLIED SOFT COMPUTING": "2.612",
    "NEUROINFORMATICS": "2.973",
    "LANG RESOUR EVAL": "0.308",
    "LANGUAGE RESOURCES AND EVALUATION": "0.308",
    "COMPUT CONCRETE": "1.015",
    "COMPUTERS AND CONCRETE": "1.015",
    "CIN-COMPUT INFORM NU": "0.831",
    "CIN-COMPUTERS INFORMATICS NURSING": "0.831",
    "J COMPUT INF SCI ENG": "0.511",
    "JOURNAL OF COMPUTING AND INFORMATION SCIENCE IN ENGINEERING": "0.511",
    "J BIOMED INFORM": "1.792",
    "JOURNAL OF BIOMEDICAL INFORMATICS": "1.792",
    "COMPUT SCI ENG": "1.422",
    "COMPUTING IN SCIENCE & ENGINEERING": "1.422",
    "QSAR COMB SCI": "1.550",
    "QSAR & COMBINATORIAL SCIENCE": "1.550",
    "STRUCT MULTIDISCIP O": "1.488",
    "STRUCTURAL AND MULTIDISCIPLINARY OPTIMIZATION": "1.488",
    "J MOL MODEL": "1.797",
    "JOURNAL OF MOLECULAR MODELING": "1.797",
    "ROBOT CIM-INT MANUF": "1.173",
    "ROBOTICS AND COMPUTER-INTEGRATED MANUFACTURING": "1.173",
    "COMPUT MATH APPL": "1.747",
    "COMPUTERS & MATHEMATICS WITH APPLICATIONS": "1.747",
    "AI EDAM": "0.786",
    "AI EDAM-ARTIFICIAL INTELLIGENCE FOR ENGINEERING DESIGN ANALYSIS AND MANUFAC": "0.786",
    "COMPUT LINGUIST": "0.721",
    "COMPUTATIONAL LINGUISTICS": "0.721",
    "J COMPUT CIVIL ENG": "1.337",
    "JOURNAL OF COMPUTING IN CIVIL ENGINEERING": "1.337",
    "SOC SCI COMPUT REV": "1.075",
    "SOCIAL SCIENCE COMPUTER REVIEW": "1.075",
    "J COMPUT AID MOL DES": "3.386",
    "JOURNAL OF COMPUTER-AIDED MOLECULAR DESIGN": "3.386",
    "INT J COMPUT INTEG M": "1.071",
    "INTERNATIONAL JOURNAL OF COMPUTER INTEGRATED MANUFACTURING": "1.071",
    "J COMPUT-AIDED MATER": "",
    "JOURNAL OF COMPUTER-AIDED MATERIALS DESIGN": "",
    "J NEW MUSIC RES": "0.481",
    "JOURNAL OF NEW MUSIC RESEARCH": "0.481",
    "NETWORKS": "0.983",
    "IEEE T VLSI SYST": "1.219",
    "IEEE TRANSACTIONS ON VERY LARGE SCALE INTEGRATION (VLSI) SYSTEMS": "1.219",
    "IEEE T COMPUT": "1.103",
    "IEEE TRANSACTIONS ON COMPUTERS": "1.103",
    "IBM J RES DEV": "0.723",
    "IBM JOURNAL OF RESEARCH AND DEVELOPMENT": "0.723",
    "DISPLAYS": "0.846",
    "INTEGRATION": "0.646",
    "INTEGRATION-THE VLSI JOURNAL": "0.646",
    "J CIRCUIT SYST COMP": "0.281",
    "JOURNAL OF CIRCUITS SYSTEMS AND COMPUTERS": "0.281",
    "J SYST ARCHITECT": "0.444",
    "JOURNAL OF SYSTEMS ARCHITECTURE": "0.444",
    "IEEE DES TEST COMPUT": "1.386",
    "IEEE DESIGN & TEST OF COMPUTERS": "1.386",
    "CAN J ELECT COMPUT E": "0.241",
    "CANADIAN JOURNAL OF ELECTRICAL AND COMPUTER ENGINEERING-REVUE CANADIENNE DE": "0.241",
    "ANALOG INTEGR CIRC S": "0.592",
    "ANALOG INTEGRATED CIRCUITS AND SIGNAL PROCESSING": "0.592",
    "ANN MATH ARTIF INTEL": "0.358",
    "ANNALS OF MATHEMATICS AND ARTIFICIAL INTELLIGENCE": "0.358",
    "ADAPT BEHAV": "1.019",
    "ADAPTIVE BEHAVIOR": "1.019",
    "J ARTIF INTELL RES": "1.143",
    "JOURNAL OF ARTIFICIAL INTELLIGENCE RESEARCH": "1.143",
    "COMPUT VIS IMAGE UND": "1.340",
    "COMPUTER VISION AND IMAGE UNDERSTANDING": "1.340",
    "INTELL DATA ANAL": "0.448",
    "INTELLIGENT DATA ANALYSIS": "0.448",
    "PATTERN RECOGN": "2.292",
    "PATTERN RECOGNITION": "2.292",
    "IEEE T FUZZY SYST": "4.260",
    "IEEE TRANSACTIONS ON FUZZY SYSTEMS": "4.260",
    "IEEE T IMAGE PROCESS": "3.042",
    "IEEE TRANSACTIONS ON IMAGE PROCESSING": "3.042",
    "ARTIF INTELL": "2.252",
    "ARTIFICIAL INTELLIGENCE": "2.252",
    "J INTELL FUZZY SYST": "0.556",
    "JOURNAL OF INTELLIGENT & FUZZY SYSTEMS": "0.556",
    "INTELL AUTOM SOFT CO": "0.116",
    "INTELLIGENT AUTOMATION AND SOFT COMPUTING": "0.116",
    "IEEE T PATTERN ANAL": "4.908",
    "IEEE TRANSACTIONS ON PATTERN ANALYSIS AND MACHINE INTELLIGENCE": "4.908",
    "INT J NEURAL SYST": "4.284",
    "INTERNATIONAL JOURNAL OF NEURAL SYSTEMS": "4.284",
    "J AUTOM REASONING": "0.714",
    "JOURNAL OF AUTOMATED REASONING": "0.714",
    "PATTERN RECOGN LETT": "1.034",
    "PATTERN RECOGNITION LETTERS": "1.034",
    "CHEMOMETR INTELL LAB": "1.920",
    "CHEMOMETRICS AND INTELLIGENT LABORATORY SYSTEMS": "1.920",
    "KNOWL ENG REV": "0.545",
    "KNOWLEDGE ENGINEERING REVIEW": "0.545",
    "NEURAL NETW WORLD": "0.646",
    "NEURAL NETWORK WORLD": "0.646",
    "ARTIF INTELL REV": "1.213",
    "ARTIFICIAL INTELLIGENCE REVIEW": "1.213",
    "INT J PATTERN RECOGN": "0.624",
    "INTERNATIONAL JOURNAL OF PATTERN RECOGNITION AND ARTIFICIAL INTELLIGENCE": "0.624",
    "INT J UNCERTAIN FUZZ": "1.781",
    "INTERNATIONAL JOURNAL OF UNCERTAINTY FUZZINESS AND KNOWLEDGE-BASED SYSTEMS": "1.781",
    "COGN SYST RES": "1.173",
    "COGNITIVE SYSTEMS RESEARCH": "1.173",
    "AUTON AGENT MULTI-AG": "1.213",
    "AUTONOMOUS AGENTS AND MULTI-AGENT SYSTEMS": "1.213",
    "COMPUT INFORM": "0.239",
    "COMPUTING AND INFORMATICS": "0.239",
    "INT J INNOV COMPUT I": "",
    "INTERNATIONAL JOURNAL OF INNOVATIVE COMPUTING INFORMATION AND CONTROL": "",
    "NEURAL PROCESS LETT": "0.750",
    "NEURAL PROCESSING LETTERS": "0.750",
    "ADV ENG INFORM": "1.489",
    "ADVANCED ENGINEERING INFORMATICS": "1.489",
    "INT J DOC ANAL RECOG": "0.405",
    "INTERNATIONAL JOURNAL ON DOCUMENT ANALYSIS AND RECOGNITION": "0.405",
    "ENG INTELL SYST ELEC": "",
    "ENGINEERING INTELLIGENT SYSTEMS FOR ELECTRICAL ENGINEERING AND COMMUNICATIO": "",
    "PATTERN ANAL APPL": "0.739",
    "PATTERN ANALYSIS AND APPLICATIONS": "0.739",
    "J MACH LEARN RES": "2.561",
    "JOURNAL OF MACHINE LEARNING RESEARCH": "2.561",
    "IEEE INTELL SYST": "2.154",
    "IEEE INTELLIGENT SYSTEMS": "2.154",
    "IEEE COMPUT INTELL M": "3.368",
    "IEEE COMPUTATIONAL INTELLIGENCE MAGAZINE": "3.368",
    "IET COMPUT VIS": "0.636",
    "IET COMPUTER VISION": "0.636",
    "AI MAG": "0.808",
    "AI MAGAZINE": "0.808",
    "NEURAL NETWORKS": "2.182",
    "COMPUT SPEECH LANG": "1.319",
    "COMPUTER SPEECH AND LANGUAGE": "1.319",
    "COMPUT INTELL": "0.971",
    "COMPUTATIONAL INTELLIGENCE": "0.971",
    "MACH LEARN": "1.587",
    "MACHINE LEARNING": "1.587",
    "INT J APPROX REASON": "1.948",
    "INTERNATIONAL JOURNAL OF APPROXIMATE REASONING": "1.948",
    "NEURAL COMPUT": "1.884",
    "NEURAL COMPUTATION": "1.884",
    "J CHEMOMETR": "1.952",
    "JOURNAL OF CHEMOMETRICS": "1.952",
    "APPL ARTIF INTELL": "0.333",
    "APPLIED ARTIFICIAL INTELLIGENCE": "0.333",
    "INT J INTELL SYST": "1.653",
    "INTERNATIONAL JOURNAL OF INTELLIGENT SYSTEMS": "1.653",
    "MIND MACH": "0.310",
    "MINDS AND MACHINES": "0.310",
    "J EXP THEOR ARTIF IN": "0.333",
    "JOURNAL OF EXPERIMENTAL & THEORETICAL ARTIFICIAL INTELLIGENCE": "0.333",
    "NEURAL COMPUT APPL": "0.699",
    "NEURAL COMPUTING & APPLICATIONS": "0.699",
    "ROBOT AUTON SYST": "1.056",
    "ROBOTICS AND AUTONOMOUS SYSTEMS": "1.056",
    "NEUROCOMPUTING": "1.580",
    "MECHATRONICS": "1.255",
    "ENG APPL ARTIF INTEL": "1.665",
    "ENGINEERING APPLICATIONS OF ARTIFICIAL INTELLIGENCE": "1.665",
    "KNOWL-BASED SYST": "2.422",
    "KNOWLEDGE-BASED SYSTEMS": "2.422",
    "APPL INTELL": "0.849",
    "APPLIED INTELLIGENCE": "0.849",
    "INT J COMPUT VISION": "3.741",
    "INTERNATIONAL JOURNAL OF COMPUTER VISION": "3.741",
    "J INTELL ROBOT SYST": "0.829",
    "JOURNAL OF INTELLIGENT & ROBOTIC SYSTEMS": "0.829",
    "NETWORK-COMP NEURAL": "1.533",
    "NETWORK-COMPUTATION IN NEURAL SYSTEMS": "1.533",
    "AI COMMUN": "0.500",
    "AI COMMUNICATIONS": "0.500",
    "AUTON ROBOT": "1.500",
    "AUTONOMOUS ROBOTS": "1.500",
    "EXPERT SYST APPL": "2.203",
    "EXPERT SYSTEMS WITH APPLICATIONS": "2.203",
    "ARTIF INTELL MED": "1.345",
    "ARTIFICIAL INTELLIGENCE IN MEDICINE": "1.345",
    "J INTELL MANUF": "0.859",
    "JOURNAL OF INTELLIGENT MANUFACTURING": "0.859"
}